Workbook

Sheet données
A1: Tableau des charges fixes | E1: Tableau du prix des ventes | H1: Tableau des matières premières | K1: Taxes et impôts
A2: Libellé | B2: par mois | C2: par an | E2: Produit | F2: Prix | H2: Produit | I2: Coût | K2: Type | L2: Taux
A3: loyer | B3: 1000 | C3: 12000 | E3: menu 1 | F3: 15 | H3: menu 1 | I3: 10 | K3: taxe menu | L3: 0.1
A4: cuisine | B4: 250 | C4: 3000 | E4: menu 2 | F4: 25 | H4: menu 2 | I4: 15 | K4: taxe boisson | L4: 0.2
A5: factures edf eau | B5: 200 | C5: 2400 | E5: menu 3 | F5: 35 | H5: menu 3 | I5: 20
A6: entretien | B6: 100 | C6: 1200 | E6: soft | F6: 3 | H6: soft | I6: 1
A7: publicité | B7: 66.666667 | C7: 800 | E7: alcool | F7: 6 | H7: alcool | I7: 2
A8: prime assurance | B8: 100 | C8: 1200
A9: emprunt bancaire | B9: 250 | C9: 3000
A10: personnel | B10: 2730 | C10: 32760
A11: TOTAL | B11: =SUM(B3:B10) -> 4696.6667 | C11: =SUM(C3:C10) -> 56360
A14: Tableau répartition des ventes
A15: Produit | B15: Jan | C15: Fév | D15: Mars | E15: Avr | F15: Mai | G15: Juin | H15: Juil | I15: Août | J15: Sept | K15: Oct | L15: Nov | M15: Déc
A16: Menu 1 | B16: 130 | C16: 70 | D16: 250 | E16: 220 | F16: 70 | G16: 150 | H16: 100 | I16: 240 | J16: 60 | K16: 70 | L16: 100 | M16: 130
A17: Menu 2 | B17: 90 | C17: 90 | D17: 210 | E17: 80 | F17: 160 | G17: 140 | H17: 200 | I17: 150 | J17: 90 | K17: 170 | L17: 230 | M17: 60
A18: Menu 3 | B18: 80 | C18: 130 | D18: 180 | E18: 90 | F18: 210 | G18: 250 | H18: 70 | I18: 140 | J18: 80 | K18: 60 | L18: 190 | M18: 130
A19: Soft | B19: 130 | C19: 250 | D19: 60 | E19: 190 | F19: 250 | G19: 130 | H19: 170 | I19: 110 | J19: 150 | K19: 60 | L19: 210 | M19: 60
A20: Alcool | B20: 130 | C20: 180 | D20: 140 | E20: 240 | F20: 90 | G20: 180 | H20: 170 | I20: 90 | J20: 140 | K20: 220 | L20: 140 | M20: 190

Sheet bilan 2016
A1: Libellés | B1: Jan | C1: Fév | D1: Mars | E1: Avr | F1: Mai | G1: Juin | H1: Juil | I1: Août | J1: Sept | K1: Oct | L1: Nov | M1: Déc | N1: TOTAL
A2: CA menu 1 | B2: ='données'!B16*'données'!$F$3 -> 1950 | C2: ='données'!C16*'données'!$F$3 -> 1050 | D2: ='données'!D16*'données'!$F$3 -> 3750 | E2: ='données'!E16*'données'!$F$3 -> 3300 | F2: ='données'!F16*'données'!$F$3 -> 1050 | G2: ='données'!G16*'données'!$F$3 -> 2250 | H2: ='données'!H16*'données'!$F$3 -> 1500 | I2: ='données'!I16*'données'!$F$3 -> 3600 | ... M2: ='données'!M16*'données'!$F$3 -> 1950 | N2: =SUM(B2:M2) -> 23850
A3: CA menu 2 | B3: ='données'!B17*'données'!$F$4 -> 2250 | C3: ='données'!C17*'données'!$F$4 -> 2250 | D3: ='données'!D17*'données'!$F$4 -> 5250 | E3: ='données'!E17*'données'!$F$4 -> 2000 | F3: ='données'!F17*'données'!$F$4 -> 4000 | G3: ='données'!G17*'données'!$F$4 -> 3500 | H3: ='données'!H17*'données'!$F$4 -> 5000 | I3: ='données'!I17*'données'!$F$4 -> 3750 | ... M3: ='données'!M17*'données'!$F$4 -> 1500 | N3: =SUM(B3:M3) -> 41750
A4: CA menu 3 | B4: ='données'!B18*'données'!$F$5 -> 2800 | C4: ='données'!C18*'données'!$F$5 -> 4550 | D4: ='données'!D18*'données'!$F$5 -> 6300 | E4: ='données'!E18*'données'!$F$5 -> 3150 | F4: ='données'!F18*'données'!$F$5 -> 7350 | G4: ='données'!G18*'données'!$F$5 -> 8750 | H4: ='données'!H18*'données'!$F$5 -> 2450 | I4: ='données'!I18*'données'!$F$5 -> 4900 | ... M4: ='données'!M18*'données'!$F$5 -> 4550 | N4: =SUM(B4:M4) -> 56350
A5: CA soft | B5: ='données'!B19*'données'!$F$6 -> 390 | C5: ='données'!C19*'données'!$F$6 -> 750 | D5: ='données'!D19*'données'!$F$6 -> 180 | E5: ='données'!E19*'données'!$F$6 -> 570 | F5: ='données'!F19*'données'!$F$6 -> 750 | G5: ='données'!G19*'données'!$F$6 -> 390 | H5: ='données'!H19*'données'!$F$6 -> 510 | I5: ='données'!I19*'données'!$F$6 -> 330 | ... M5: ='données'!M19*'données'!$F$6 -> 180 | N5: =SUM(B5:M5) -> 5310
A6: CA alcool | B6: ='données'!B20*'données'!$F$7 -> 780 | C6: ='données'!C20*'données'!$F$7 -> 1080 | D6: ='données'!D20*'données'!$F$7 -> 840 | E6: ='données'!E20*'données'!$F$7 -> 1440 | F6: ='données'!F20*'données'!$F$7 -> 540 | G6: ='données'!G20*'données'!$F$7 -> 1080 | H6: ='données'!H20*'données'!$F$7 -> 1020 | I6: ='données'!I20*'données'!$F$7 -> 540 | ... M6: ='données'!M20*'données'!$F$7 -> 1140 | N6: =SUM(B6:M6) -> 11460
A7: TOTAL CA | B7: =SUM(B2:B6) -> 8170 | C7: =SUM(C2:C6) -> 9680 | D7: =SUM(D2:D6) -> 16320 | E7: =SUM(E2:E6) -> 10460 | F7: =SUM(F2:F6) -> 13690 | G7: =SUM(G2:G6) -> 15970 | H7: =SUM(H2:H6) -> 10480 | I7: =SUM(I2:I6) -> 13120 | ... M7: =SUM(M2:M6) -> 9320 | N7: =SUM(B7:M7) -> 138720
A8: Charge fixe | B8: ='données'!$B$11 -> 4696.6667 | C8: ='données'!$B$11 -> 4696.6667 | D8: ='données'!$B$11 -> 4696.6667 | E8: ='données'!$B$11 -> 4696.6667 | F8: ='données'!$B$11 -> 4696.6667 | G8: ='données'!$B$11 -> 4696.6667 | H8: ='données'!$B$11 -> 4696.6667 | I8: ='données'!$B$11 -> 4696.6667 | ... M8: ='données'!$B$11 -> 4696.6667 | N8: =SUM(B8:M8) -> 56360
A9: matière 1ère menu 1 | B9: ='données'!B16*'données'!$I$3 -> 1300 | C9: ='données'!C16*'données'!$I$3 -> 700 | D9: ='données'!D16*'données'!$I$3 -> 2500 | E9: ='données'!E16*'données'!$I$3 -> 2200 | F9: ='données'!F16*'données'!$I$3 -> 700 | G9: ='données'!G16*'données'!$I$3 -> 1500 | H9: ='données'!H16*'données'!$I$3 -> 1000 | I9: ='données'!I16*'données'!$I$3 -> 2400 | ... M9: ='données'!M16*'données'!$I$3 -> 1300 | N9: =SUM(B9:M9) -> 15900
A10: matière 1ère menu 2 | B10: ='données'!B17*'données'!$I$4 -> 1350 | C10: ='données'!C17*'données'!$I$4 -> 1350 | D10: ='données'!D17*'données'!$I$4 -> 3150 | E10: ='données'!E17*'données'!$I$4 -> 1200 | F10: ='données'!F17*'données'!$I$4 -> 2400 | G10: ='données'!G17*'données'!$I$4 -> 2100 | H10: ='données'!H17*'données'!$I$4 -> 3000 | I10: ='données'!I17*'données'!$I$4 -> 2250 | ... M10: ='données'!M17*'données'!$I$4 -> 900 | N10: =SUM(B10:M10) -> 25050
A11: matière 1ère menu 3 | B11: ='données'!B18*'données'!$I$5 -> 1600 | C11: ='données'!C18*'données'!$I$5 -> 2600 | D11: ='données'!D18*'données'!$I$5 -> 3600 | E11: ='données'!E18*'données'!$I$5 -> 1800 | F11: ='données'!F18*'données'!$I$5 -> 4200 | G11: ='données'!G18*'données'!$I$5 -> 5000 | H11: ='données'!H18*'données'!$I$5 -> 1400 | I11: ='données'!I18*'données'!$I$5 -> 2800 | ... M11: ='données'!M18*'données'!$I$5 -> 2600 | N11: =SUM(B11:M11) -> 32200
A12: matière 1ère soft | B12: ='données'!B19*'données'!$I$6 -> 130 | C12: ='données'!C19*'données'!$I$6 -> 250 | D12: ='données'!D19*'données'!$I$6 -> 60 | E12: ='données'!E19*'données'!$I$6 -> 190 | F12: ='données'!F19*'données'!$I$6 -> 250 | G12: ='données'!G19*'données'!$I$6 -> 130 | H12: ='données'!H19*'données'!$I$6 -> 170 | I12: ='données'!I19*'données'!$I$6 -> 110 | ... M12: ='données'!M19*'données'!$I$6 -> 60 | N12: =SUM(B12:M12) -> 1770
A13: matière 1ère alcool | B13: ='données'!B20*'données'!$I$7 -> 260 | C13: ='données'!C20*'données'!$I$7 -> 360 | D13: ='données'!D20*'données'!$I$7 -> 280 | E13: ='données'!E20*'données'!$I$7 -> 480 | F13: ='données'!F20*'données'!$I$7 -> 180 | G13: ='données'!G20*'données'!$I$7 -> 360 | H13: ='données'!H20*'données'!$I$7 -> 340 | I13: ='données'!I20*'données'!$I$7 -> 180 | ... M13: ='données'!M20*'données'!$I$7 -> 380 | N13: =SUM(B13:M13) -> 3820
A14: taxe menu | B14: =SUM(B2:B4)*'données'!$L$3 -> 700 | C14: =SUM(C2:C4)*'données'!$L$3 -> 785 | D14: =SUM(D2:D4)*'données'!$L$3 -> 1530 | E14: =SUM(E2:E4)*'données'!$L$3 -> 845 | F14: =SUM(F2:F4)*'données'!$L$3 -> 1240 | G14: =SUM(G2:G4)*'données'!$L$3 -> 1450 | H14: =SUM(H2:H4)*'données'!$L$3 -> 895 | I14: =SUM(I2:I4)*'données'!$L$3 -> 1225 | ... M14: =SUM(M2:M4)*'données'!$L$3 -> 800 | N14: =SUM(B14:M14) -> 12195
A15: taxe boisson | B15: =SUM(B5:B6)*'données'!$L$4 -> 234 | C15: =SUM(C5:C6)*'données'!$L$4 -> 366 | D15: =SUM(D5:D6)*'données'!$L$4 -> 204 | E15: =SUM(E5:E6)*'données'!$L$4 -> 402 | F15: =SUM(F5:F6)*'données'!$L$4 -> 258 | G15: =SUM(G5:G6)*'données'!$L$4 -> 294 | H15: =SUM(H5:H6)*'données'!$L$4 -> 306 | I15: =SUM(I5:I6)*'données'!$L$4 -> 174 | ... M15: =SUM(M5:M6)*'données'!$L$4 -> 264 | N15: =SUM(B15:M15) -> 3354
A16: charge variable | B16: =SUM(B9:B15) -> 5574 | C16: =SUM(C9:C15) -> 6411 | D16: =SUM(D9:D15) -> 11324 | E16: =SUM(E9:E15) -> 7117 | F16: =SUM(F9:F15) -> 9228 | G16: =SUM(G9:G15) -> 10834 | H16: =SUM(H9:H15) -> 7111 | I16: =SUM(I9:I15) -> 9139 | ... M16: =SUM(M9:M15) -> 6304 | N16: =SUM(B16:M16) -> 94289
A17: total coûts | B17: =B8+B16 -> 10270.667 | C17: =C8+C16 -> 11107.667 | D17: =D8+D16 -> 16020.667 | E17: =E8+E16 -> 11813.667 | F17: =F8+F16 -> 13924.667 | G17: =G8+G16 -> 15530.667 | H17: =H8+H16 -> 11807.667 | I17: =I8+I16 -> 13835.667 | ... M17: =M8+M16 -> 11000.667 | N17: =SUM(B17:M17) -> 150649
A18: Résultat | B18: =B7-B17 -> -2100.6667 | C18: =C7-C17 -> -1427.6667 | D18: =D7-D17 -> 299.33333 | E18: =E7-E17 -> -1353.6667 | F18: =F7-F17 -> -234.66667 | G18: =G7-G17 -> 439.33333 | H18: =H7-H17 -> -1327.6667 | I18: =I7-I17 -> -715.66667 | ... M18: =M7-M17 -> -1680.6667 | N18: =SUM(B18:M18) -> -11929
